Metadata-Version: 1.1
Name: servicecontrol
Version: 0.11
Summary: Wraps any program to provide XMLRPC start/stop functionality + logging
Home-page: https://github.com/kworm1/servicecontrol
Author: Kjetil Wormnes
Author-email: kjetil@wormnes.com
License: UNKNOWN
Keywords: wrapper logging xmlrpc processcontrol process
Platform: UNKNOWN
Classifier: Development Status :: 4 - Beta
Classifier: Intended Audience :: Developers
Classifier: Topic :: System :: Logging
Classifier: Topic :: Utilities
Classifier: License :: OSI Approved :: MIT License
Classifier: Programming Language :: Python :: 2.7
